ZogPy/__init__.py
ZogPy/core.py
zogpy-0.1.0.dist-info/licenses/LICENSE
zogpy-0.1.0.dist-info/METADATA
zogpy-0.1.0.dist-info/WHEEL
zogpy-0.1.0.dist-info/top_level.txt
zogpy-0.1.0.dist-info/RECORD
