Metadata-Version: 2.4
Name: ZogPy
Version: 0.1.0
Summary: A tiny example package
Author: Tristan Hertzog
License: MIT
Project-URL: Homepage, https://github.com/Tmanhertzog/ZogPy
Requires-Python: >=3.9
License-File: LICENSE
Dynamic: license-file
